area/__init__.py
calculate_area-0.0.1.dist-info/METADATA
calculate_area-0.0.1.dist-info/WHEEL
calculate_area-0.0.1.dist-info/top_level.txt
calculate_area-0.0.1.dist-info/RECORD
