Metadata-Version: 2.1
Name: calculate_area
Version: 0.0.1
Summary: This is module for send area
Home-page: https://github.com/Dmitriy1336/Area/
Author: jaden
Author-email: dmitrijkaraulov7@gmail.com
Project-URL: GitHub, https://github.com/Dmitriy1336/Area/
Keywords: calculating area
Classifier: Programming Language :: Python :: 3.11
Classifier: License :: OSI Approved :: MIT License
Classifier: Operating System :: OS Independent
Requires-Python: >=3.6
Requires-Dist: requests >=2.25.1
